parrot_rcc/__init__.py
parrot_rcc/cli.py
parrot_rcc/types.py
parrot_rcc/utils.py
parrot_rcc-0.1.2.dist-info/entry_points.txt
parrot_rcc-0.1.2.dist-info/LICENSE
parrot_rcc-0.1.2.dist-info/WHEEL
parrot_rcc-0.1.2.dist-info/METADATA
parrot_rcc-0.1.2.dist-info/RECORD
